{
   "agent": "WSServer (HTTPs)",
   "behavior": "OK",
   "behaviorClose": "OK",
   "case": 73,
   "closedByMe": false,
   "createStats": true,
   "createWirelog": true,
   "description": "Send invalid UTF-8 text message in fragments of 1 octet, resulting in frames ending on positions which are not code point ends.<br><br>MESSAGE:<br>cebae1bdb9cf83cebcceb5eda080656469746564",
   "droppedByMe": false,
   "duration": 4,
   "expectation": "The connection is failed immediately, since the payload is not valid UTF-8.",
   "expected": {
      "OK": []
   },
   "expectedClose": {
      "closeCode": [
         1007
      ],
      "closedByMe": false,
      "closedByWrongEndpointIsFatal": true,
      "requireClean": false
   },
   "failedByMe": false,
   "httpRequest": "GET / HTTP/1.1\r\nUser-Agent: AutobahnTestSuite/0.8.1-0.10.9\r\nHost: 127.0.0.1:9011\r\nUpgrade: WebSocket\r\nConnection: Upgrade\r\nPragma: no-cache\r\nCache-Control: no-cache\r\nSec-WebSocket-Key: wr7zLR8Wp3LDMJtLGeDb9w==\r\nSec-WebSocket-Version: 13\r\n\r\n",
   "httpResponse": "HTTP/1.1 101 Switching Protocols\r\nSec-Websocket-Accept: HwCIxdA0TGp4AN1YkfNdGWUu6Vc=\r\nUpgrade: websocket\r\nConnection: Upgrade\r\nServer: WSServer/2.0.0\r\n\r\n",
   "id": "6.3.2",
   "isServer": false,
   "localCloseCode": 1000,
   "localCloseReason": null,
   "received": [],
   "remoteCloseCode": 1007,
   "remoteCloseReason": "Invalid frame payload data",
   "reportCompressionRatio": false,
   "reportTime": false,
   "result": "Actual events match at least one expected.",
   "resultClose": "Connection was properly closed",
   "rxFrameStats": {
      "8": 1
   },
   "rxOctetStats": {
      "30": 1,
      "153": 1
   },
   "started": "2020-01-29T08:53:47.812Z",
   "trafficStats": null,
   "txFrameStats": {
      "0": 20,
      "1": 1,
      "8": 1
   },
   "txOctetStats": {
      "6": 1,
      "7": 20,
      "8": 1,
      "240": 1
   },
   "wasClean": true,
   "wasCloseHandshakeTimeout": false,
   "wasNotCleanReason": null,
   "wasOpenHandshakeTimeout": false,
   "wasServerConnectionDropTimeout": false,
   "wirelog": [
      [
         "TO",
         [
            240,
            "474554202f20485454502f312e310d0a557365722d4167656e743a204175746f6261686e5465737453756974652f302e382e312d302e31302e390d0a486f7374 ..."
         ],
         false
      ],
      [
         "RO",
         [
            153,
            "485454502f312e312031303120537769746368696e672050726f746f636f6c730d0a5365632d576562736f636b65742d4163636570743a204877434978644130 ..."
         ]
      ],
      [
         "TF",
         [
            1,
            "0xce"
         ],
         1,
         false,
         0,
         "07cbdd00",
         null,
         null,
         false
      ],
      [
         "TO",
         [
            7,
            "018107cbdd00c9"
         ],
         false
      ],
      [
         "TF",
         [
            1,
            "0xba"
         ],
         0,
         false,
         0,
         "12cce2a4",
         null,
         null,
         false
      ],
      [
         "TO",
         [
            7,
            "008112cce2a4a8"
         ],
         false
      ],
      [
         "TF",
         [
            1,
            "0xe1"
         ],
         0,
         false,
         0,
         "2b14e349",
         null,
         null,
         false
      ],
      [
         "TO",
         [
            7,
            "00812b14e349ca"
         ],
         false
      ],
      [
         "TF",
         [
            1,
            "0xbd"
         ],
         0,
         false,
         0,
         "79366d8a",
         null,
         null,
         false
      ],
      [
         "TO",
         [
            7,
            "008179366d8ac4"
         ],
         false
      ],
      [
         "TF",
         [
            1,
            "0xb9"
         ],
         0,
         false,
         0,
         "f09f46ae",
         null,
         null,
         false
      ],
      [
         "TO",
         [
            7,
            "0081f09f46ae49"
         ],
         false
      ],
      [
         "TF",
         [
            1,
            "0xcf"
         ],
         0,
         false,
         0,
         "196f4854",
         null,
         null,
         false
      ],
      [
         "TO",
         [
            7,
            "0081196f4854d6"
         ],
         false
      ],
      [
         "TF",
         [
            1,
            "0x83"
         ],
         0,
         false,
         0,
         "d91ac3d1",
         null,
         null,
         false
      ],
      [
         "TO",
         [
            7,
            "0081d91ac3d15a"
         ],
         false
      ],
      [
         "TF",
         [
            1,
            "0xce"
         ],
         0,
         false,
         0,
         "a2d72597",
         null,
         null,
         false
      ],
      [
         "TO",
         [
            7,
            "0081a2d725976c"
         ],
         false
      ],
      [
         "TF",
         [
            1,
            "0xbc"
         ],
         0,
         false,
         0,
         "cb9c29cd",
         null,
         null,
         false
      ],
      [
         "TO",
         [
            7,
            "0081cb9c29cd77"
         ],
         false
      ],
      [
         "TF",
         [
            1,
            "0xce"
         ],
         0,
         false,
         0,
         "4e92ae08",
         null,
         null,
         false
      ],
      [
         "TO",
         [
            7,
            "00814e92ae0880"
         ],
         false
      ],
      [
         "TF",
         [
            1,
            "0xb5"
         ],
         0,
         false,
         0,
         "79d6b5a9",
         null,
         null,
         false
      ],
      [
         "TO",
         [
            7,
            "008179d6b5a9cc"
         ],
         false
      ],
      [
         "TF",
         [
            1,
            "0xed"
         ],
         0,
         false,
         0,
         "28aa546b",
         null,
         null,
         false
      ],
      [
         "TO",
         [
            7,
            "008128aa546bc5"
         ],
         false
      ],
      [
         "TF",
         [
            1,
            "0xa0"
         ],
         0,
         false,
         0,
         "30689cad",
         null,
         null,
         false
      ],
      [
         "TO",
         [
            7,
            "008130689cad90"
         ],
         false
      ],
      [
         "TF",
         [
            1,
            "0x80"
         ],
         0,
         false,
         0,
         "b8222535",
         null,
         null,
         false
      ],
      [
         "TO",
         [
            7,
            "0081b822253538"
         ],
         false
      ],
      [
         "TF",
         [
            1,
            "e"
         ],
         0,
         false,
         0,
         "ff0a2235",
         null,
         null,
         false
      ],
      [
         "TO",
         [
            7,
            "0081ff0a22359a"
         ],
         false
      ],
      [
         "TF",
         [
            1,
            "d"
         ],
         0,
         false,
         0,
         "e6a6c1d0",
         null,
         null,
         false
      ],
      [
         "TO",
         [
            7,
            "0081e6a6c1d082"
         ],
         false
      ],
      [
         "TF",
         [
            1,
            "i"
         ],
         0,
         false,
         0,
         "e4173bca",
         null,
         null,
         false
      ],
      [
         "TO",
         [
            7,
            "0081e4173bca8d"
         ],
         false
      ],
      [
         "TF",
         [
            1,
            "t"
         ],
         0,
         false,
         0,
         "44f3f4f7",
         null,
         null,
         false
      ],
      [
         "TO",
         [
            7,
            "008144f3f4f730"
         ],
         false
      ],
      [
         "TF",
         [
            1,
            "e"
         ],
         0,
         false,
         0,
         "16d5de92",
         null,
         null,
         false
      ],
      [
         "TO",
         [
            7,
            "008116d5de9273"
         ],
         false
      ],
      [
         "TF",
         [
            1,
            "d"
         ],
         0,
         false,
         0,
         "d3075031",
         null,
         null,
         false
      ],
      [
         "TO",
         [
            7,
            "0081d3075031b7"
         ],
         false
      ],
      [
         "TF",
         [
            0,
            ""
         ],
         0,
         true,
         0,
         "5f5fc984",
         null,
         null,
         false
      ],
      [
         "TO",
         [
            6,
            "80805f5fc984"
         ],
         false
      ],
      [
         "KL",
         1
      ],
      [
         "RO",
         [
            30,
            "881c03ef496e76616c6964206672616d65207061796c6f61642064617461"
         ]
      ],
      [
         "RF",
         [
            28,
            "0x03ef496e76616c6964206672616d65207061796c6f61642064617461"
         ],
         8,
         true,
         0,
         false,
         null
      ],
      [
         "TF",
         [
            2,
            "0x03e8"
         ],
         8,
         true,
         0,
         "bf69f6c8",
         null,
         null,
         false
      ],
      [
         "TO",
         [
            8,
            "8882bf69f6c8bc81"
         ],
         false
      ]
   ]
}