{
   "agent": "WSServer (HTTP)",
   "behavior": "OK",
   "behaviorClose": "OK",
   "case": 386,
   "closedByMe": true,
   "createStats": true,
   "createWirelog": true,
   "description": "Send 1000 compressed messages each of payload size 32768, auto-fragment to 256 octets. Use default permessage-deflate offer.",
   "droppedByMe": false,
   "duration": 5056,
   "expectation": "Receive echo'ed messages (with payload as sent). Timeout case after 480 secs.",
   "expected": {},
   "expectedClose": {
      "closeCode": [
         1000
      ],
      "closedByMe": true,
      "requireClean": true
   },
   "failedByMe": false,
   "httpRequest": "GET / HTTP/1.1\r\nUser-Agent: AutobahnTestSuite/0.8.1-0.10.9\r\nHost: 127.0.0.1:9010\r\nUpgrade: WebSocket\r\nConnection: Upgrade\r\nPragma: no-cache\r\nCache-Control: no-cache\r\nSec-WebSocket-Key: 6CTlsOkpBz0o+pwkSQqpvA==\r\nSec-WebSocket-Extensions: permessage-deflate; client_no_context_takeover; client_max_window_bits\r\nSec-WebSocket-Version: 13\r\n\r\n",
   "httpResponse": "HTTP/1.1 101 Switching Protocols\r\nSec-Websocket-Extensions: permessage-deflate;client_no_context_takeover;client_max_window_bits=10;server_max_window_bits=10\r\nSec-Websocket-Accept: SxQfYor+gvPmkUrTOW76VZeNlZc=\r\nUpgrade: websocket\r\nConnection: Upgrade\r\nServer: WSServer/2.0.0\r\n\r\n",
   "id": "12.5.13",
   "isServer": false,
   "localCloseCode": 1000,
   "localCloseReason": null,
   "received": [],
   "remoteCloseCode": 1000,
   "remoteCloseReason": null,
   "reportCompressionRatio": true,
   "reportTime": true,
   "result": "Ok, received all echo'ed messages in time.",
   "resultClose": "Connection was properly closed",
   "rxFrameStats": {
      "2": 1000,
      "8": 1
   },
   "rxOctetStats": {
      "4": 1,
      "278": 1,
      "6991": 1,
      "7353": 1,
      "7357": 1,
      "7442": 1,
      "7459": 1,
      "7553": 1,
      "7576": 1,
      "7616": 1,
      "7626": 1,
      "7811": 1,
      "7854": 1,
      "7984": 1,
      "7995": 1,
      "7999": 1,
      "8016": 1,
      "8071": 1,
      "8074": 1,
      "8092": 1,
      "8132": 1,
      "8148": 1,
      "8194": 1,
      "8200": 1,
      "8216": 1,
      "8270": 1,
      "8279": 1,
      "8285": 1,
      "8332": 1,
      "8334": 1,
      "8356": 1,
      "8362": 2,
      "8366": 1,
      "8367": 2,
      "8373": 1,
      "8379": 1,
      "8384": 1,
      "8392": 1,
      "8398": 2,
      "8399": 1,
      "8412": 1,
      "8418": 1,
      "8437": 1,
      "8448": 1,
      "8456": 1,
      "8487": 1,
      "8493": 1,
      "8583": 1,
      "8590": 1,
      "8591": 1,
      "8621": 1,
      "8628": 1,
      "8649": 1,
      "8667": 1,
      "8688": 1,
      "8724": 1,
      "8725": 1,
      "8744": 1,
      "8838": 1,
      "8962": 1,
      "9164": 1,
      "9238": 1,
      "9925": 1,
      "9976": 1,
      "10095": 1,
      "10210": 1,
      "10260": 1,
      "11185": 1,
      "11228": 1,
      "11343": 1,
      "11385": 1,
      "11415": 1,
      "12024": 1,
      "12058": 1,
      "12173": 1,
      "12181": 1,
      "12195": 1,
      "12223": 1,
      "12297": 1,
      "12338": 1,
      "12450": 1,
      "12861": 1,
      "13072": 1,
      "13138": 1,
      "13320": 1,
      "13604": 1,
      "13637": 1,
      "13712": 1,
      "14112": 1,
      "14146": 1,
      "14542": 1,
      "14830": 1,
      "14943": 1,
      "15261": 1,
      "15349": 1,
      "15377": 1,
      "15547": 1,
      "15671": 1,
      "16070": 1,
      "16140": 1,
      "16243": 1,
      "16491": 1,
      "16589": 1,
      "16946": 1,
      "17042": 1,
      "17073": 1,
      "17147": 1,
      "17227": 1,
      "17537": 1,
      "18040": 1,
      "18084": 1,
      "18409": 1,
      "18663": 1,
      "18811": 1,
      "19216": 1,
      "19220": 1,
      "19565": 1,
      "19589": 1,
      "19654": 1,
      "19685": 1,
      "19704": 1,
      "20014": 1,
      "20124": 1,
      "20647": 1,
      "20661": 1,
      "20746": 1,
      "20751": 1,
      "20887": 1,
      "20950": 1,
      "20960": 1,
      "20983": 1,
      "20984": 2,
      "20985": 1,
      "21004": 1,
      "21012": 1,
      "21021": 1,
      "21029": 1,
      "21030": 1,
      "21032": 1,
      "21048": 1,
      "21055": 1,
      "21071": 1,
      "21076": 1,
      "21081": 1,
      "21093": 1,
      "21096": 1,
      "21223": 1,
      "21331": 1,
      "21518": 1,
      "21794": 1,
      "21843": 1,
      "21875": 1,
      "21938": 1,
      "22307": 1,
      "22312": 1,
      "22414": 1,
      "22430": 1,
      "22493": 1,
      "22533": 1,
      "22589": 1,
      "22766": 1,
      "22820": 1,
      "23035": 1,
      "23192": 1,
      "23256": 1,
      "23268": 1,
      "23403": 1,
      "23429": 1,
      "23465": 1,
      "23484": 1,
      "23557": 1,
      "23575": 1,
      "23674": 1,
      "23746": 1,
      "23807": 1,
      "23872": 1,
      "24052": 1,
      "24152": 1,
      "24171": 1,
      "24557": 1,
      "24712": 1,
      "24841": 1,
      "24918": 1,
      "24938": 1,
      "24948": 1,
      "25001": 1,
      "25242": 1,
      "25269": 1,
      "25312": 1,
      "25581": 1,
      "25621": 1,
      "25650": 1,
      "25697": 1,
      "25700": 1,
      "25799": 1,
      "25950": 1,
      "26010": 1,
      "26019": 1,
      "26111": 1,
      "26339": 1,
      "26370": 1,
      "26372": 1,
      "26417": 1,
      "26422": 1,
      "26428": 1,
      "26441": 1,
      "26443": 1,
      "26445": 1,
      "26517": 1,
      "26540": 1,
      "26563": 1,
      "26592": 1,
      "26617": 1,
      "26660": 1,
      "26669": 1,
      "26672": 1,
      "26686": 1,
      "26693": 1,
      "26703": 1,
      "26713": 1,
      "26717": 1,
      "26719": 1,
      "26738": 1,
      "26743": 1,
      "26746": 1,
      "26753": 1,
      "26770": 1,
      "26794": 1,
      "26804": 1,
      "26818": 1,
      "26824": 1,
      "26838": 1,
      "26840": 1,
      "26841": 1,
      "26842": 1,
      "26844": 1,
      "26845": 1,
      "26846": 1,
      "26852": 1,
      "26879": 1,
      "26885": 1,
      "26888": 1,
      "26890": 1,
      "26907": 2,
      "26912": 1,
      "26916": 2,
      "26932": 1,
      "26942": 3,
      "26943": 1,
      "26947": 1,
      "26953": 1,
      "26961": 1,
      "26962": 1,
      "26970": 1,
      "26976": 1,
      "26986": 2,
      "26990": 1,
      "27000": 2,
      "27005": 1,
      "27009": 1,
      "27016": 1,
      "27018": 1,
      "27021": 1,
      "27022": 2,
      "27026": 1,
      "27036": 1,
      "27040": 1,
      "27041": 1,
      "27042": 1,
      "27043": 1,
      "27046": 1,
      "27050": 1,
      "27053": 1,
      "27060": 1,
      "27062": 1,
      "27063": 1,
      "27065": 1,
      "27066": 1,
      "27070": 1,
      "27072": 1,
      "27073": 2,
      "27077": 1,
      "27079": 2,
      "27082": 2,
      "27085": 1,
      "27088": 1,
      "27089": 2,
      "27090": 1,
      "27093": 1,
      "27094": 2,
      "27098": 1,
      "27106": 1,
      "27112": 2,
      "27116": 1,
      "27117": 1,
      "27119": 1,
      "27121": 1,
      "27125": 1,
      "27129": 1,
      "27131": 1,
      "27132": 2,
      "27133": 1,
      "27136": 2,
      "27137": 1,
      "27138": 1,
      "27140": 1,
      "27148": 3,
      "27150": 2,
      "27155": 2,
      "27158": 2,
      "27161": 1,
      "27162": 1,
      "27164": 1,
      "27166": 1,
      "27167": 1,
      "27170": 1,
      "27171": 1,
      "27172": 1,
      "27175": 1,
      "27180": 1,
      "27183": 1,
      "27185": 1,
      "27186": 1,
      "27187": 1,
      "27191": 2,
      "27196": 1,
      "27199": 1,
      "27200": 2,
      "27202": 1,
      "27209": 1,
      "27210": 1,
      "27229": 1,
      "27242": 1,
      "27243": 1,
      "27244": 1,
      "27247": 1,
      "27252": 1,
      "27255": 1,
      "27258": 1,
      "27274": 1,
      "27285": 1,
      "27288": 1,
      "27292": 1,
      "27295": 1,
      "27316": 1,
      "27320": 1,
      "27332": 1,
      "27338": 1,
      "27343": 1,
      "27932": 1,
      "28029": 1,
      "28157": 1,
      "29253": 1,
      "29301": 1,
      "29381": 1,
      "29406": 1,
      "30361": 1,
      "30464": 1,
      "30680": 1,
      "31391": 1,
      "31392": 1,
      "31437": 2,
      "31496": 1,
      "31540": 1,
      "31596": 1,
      "31597": 1,
      "31640": 1,
      "31815": 2,
      "31841": 1,
      "31842": 1,
      "31849": 1,
      "31861": 1,
      "31862": 1,
      "31865": 1,
      "31868": 1,
      "31869": 1,
      "31870": 1,
      "31871": 1,
      "31872": 1,
      "31882": 1,
      "31883": 3,
      "31884": 3,
      "31899": 1,
      "31910": 1,
      "31911": 1,
      "31916": 1,
      "31918": 1,
      "31926": 1,
      "31934": 1,
      "31935": 2,
      "31936": 3,
      "31937": 3,
      "31938": 1,
      "31939": 1,
      "31940": 2,
      "31948": 1,
      "31949": 1,
      "31951": 1,
      "31953": 1,
      "31955": 2,
      "31957": 1,
      "31958": 1,
      "31963": 1,
      "31964": 1,
      "31965": 1,
      "31966": 1,
      "31969": 1,
      "31970": 1,
      "31971": 2,
      "31972": 1,
      "31973": 1,
      "31974": 3,
      "31975": 2,
      "31976": 4,
      "31977": 1,
      "31978": 2,
      "31979": 1,
      "31985": 1,
      "31995": 1,
      "31997": 1,
      "32000": 3,
      "32001": 1,
      "32002": 2,
      "32003": 1,
      "32004": 1,
      "32007": 1,
      "32008": 3,
      "32010": 5,
      "32011": 1,
      "32012": 2,
      "32013": 2,
      "32014": 1,
      "32015": 2,
      "32018": 1,
      "32021": 1,
      "32024": 3,
      "32026": 1,
      "32027": 2,
      "32029": 1,
      "32031": 2,
      "32032": 1,
      "32033": 1,
      "32034": 2,
      "32035": 2,
      "32036": 1,
      "32041": 1,
      "32042": 2,
      "32043": 1,
      "32047": 1,
      "32049": 1,
      "32053": 1,
      "32054": 2,
      "32055": 1,
      "32056": 2,
      "32057": 1,
      "32058": 1,
      "32059": 1,
      "32062": 1,
      "32064": 1,
      "32066": 1,
      "32067": 1,
      "32068": 1,
      "32070": 3,
      "32071": 1,
      "32075": 1,
      "32079": 1,
      "32081": 5,
      "32082": 1,
      "32085": 1,
      "32087": 1,
      "32088": 2,
      "32089": 2,
      "32090": 1,
      "32091": 2,
      "32092": 1,
      "32093": 3,
      "32100": 2,
      "32101": 1,
      "32103": 2,
      "32104": 4,
      "32105": 4,
      "32107": 2,
      "32111": 1,
      "32113": 2,
      "32114": 1,
      "32115": 1,
      "32116": 1,
      "32118": 1,
      "32119": 2,
      "32120": 2,
      "32122": 1,
      "32125": 1,
      "32126": 2,
      "32127": 3,
      "32128": 7,
      "32130": 1,
      "32131": 1,
      "32132": 1,
      "32133": 1,
      "32143": 1,
      "32144": 3,
      "32145": 1,
      "32148": 1,
      "32149": 1,
      "32151": 1,
      "32152": 1,
      "32153": 1,
      "32154": 2,
      "32155": 4,
      "32156": 1,
      "32157": 2,
      "32158": 1,
      "32159": 1,
      "32161": 1,
      "32167": 1,
      "32169": 2,
      "32171": 2,
      "32172": 2,
      "32173": 1,
      "32174": 2,
      "32175": 1,
      "32177": 2,
      "32180": 1,
      "32181": 1,
      "32183": 3,
      "32184": 1,
      "32185": 1,
      "32187": 2,
      "32188": 1,
      "32190": 2,
      "32191": 1,
      "32193": 1,
      "32198": 2,
      "32199": 4,
      "32201": 1,
      "32202": 1,
      "32203": 1,
      "32204": 3,
      "32205": 4,
      "32206": 1,
      "32209": 2,
      "32210": 3,
      "32214": 3,
      "32215": 1,
      "32216": 2,
      "32217": 3,
      "32218": 7,
      "32219": 4,
      "32220": 1,
      "32221": 3,
      "32222": 1,
      "32223": 2,
      "32225": 2,
      "32227": 1,
      "32228": 1,
      "32231": 1,
      "32234": 1,
      "32235": 1,
      "32236": 1,
      "32238": 1,
      "32240": 2,
      "32242": 1,
      "32243": 1,
      "32246": 1,
      "32247": 1,
      "32248": 1,
      "32249": 2,
      "32250": 2,
      "32251": 3,
      "32252": 1,
      "32253": 2,
      "32254": 6,
      "32258": 1,
      "32260": 2,
      "32261": 1,
      "32262": 1,
      "32264": 2,
      "32265": 2,
      "32266": 1,
      "32268": 1,
      "32271": 1,
      "32277": 2,
      "32278": 1,
      "32279": 1,
      "32280": 2,
      "32281": 1,
      "32282": 1,
      "32283": 1,
      "32284": 1,
      "32285": 2,
      "32287": 2,
      "32291": 1,
      "32292": 1,
      "32297": 2,
      "32299": 1,
      "32300": 1,
      "32301": 1,
      "32302": 1,
      "32304": 1,
      "32310": 1,
      "32314": 1,
      "32315": 3,
      "32318": 1,
      "32320": 1,
      "32321": 1,
      "32322": 1,
      "32323": 1,
      "32324": 3,
      "32325": 1,
      "32327": 2,
      "32328": 1,
      "32329": 1,
      "32331": 1,
      "32332": 2,
      "32340": 1,
      "32341": 2,
      "32342": 2,
      "32343": 1,
      "32345": 1,
      "32347": 1,
      "32348": 1,
      "32349": 1,
      "32350": 1,
      "32351": 2,
      "32352": 1,
      "32354": 1,
      "32357": 1,
      "32358": 1,
      "32359": 2,
      "32360": 2,
      "32361": 4,
      "32362": 2,
      "32364": 2,
      "32365": 1,
      "32368": 1,
      "32369": 2,
      "32372": 1,
      "32373": 3,
      "32374": 2,
      "32375": 2,
      "32377": 1,
      "32382": 2,
      "32383": 1,
      "32384": 1,
      "32389": 1,
      "32390": 1,
      "32391": 1,
      "32392": 1,
      "32393": 1,
      "32394": 1,
      "32395": 3,
      "32396": 2,
      "32407": 2,
      "32423": 1,
      "32424": 2,
      "32425": 2,
      "32426": 1,
      "32435": 1,
      "32436": 2,
      "32437": 1,
      "32440": 1,
      "32443": 1,
      "32444": 1,
      "32446": 1,
      "32447": 3,
      "32450": 1,
      "32451": 1,
      "32452": 1,
      "32453": 2,
      "32457": 1,
      "32458": 3,
      "32465": 1,
      "32469": 1,
      "32474": 1,
      "32476": 1,
      "32480": 2,
      "32483": 2,
      "32485": 1,
      "32486": 2,
      "32512": 1,
      "32513": 1,
      "32514": 1,
      "32515": 1,
      "32516": 3,
      "32517": 1,
      "32519": 2,
      "32521": 1,
      "32523": 2,
      "32525": 1,
      "32526": 2,
      "32530": 2,
      "32531": 1,
      "32534": 3,
      "32535": 1,
      "32536": 1,
      "32537": 2,
      "32538": 2,
      "32540": 1,
      "32541": 2,
      "32545": 1,
      "32546": 2,
      "32548": 1,
      "32549": 1,
      "32550": 1,
      "32551": 1,
      "32554": 1,
      "32555": 1,
      "32556": 2,
      "32561": 2,
      "32562": 1,
      "32563": 1,
      "32566": 4,
      "32567": 2,
      "32568": 3,
      "32569": 2,
      "32570": 3,
      "32571": 1,
      "32572": 2,
      "32573": 1,
      "32584": 2,
      "32585": 1,
      "32586": 1,
      "32590": 2,
      "32594": 1,
      "32595": 1,
      "32597": 1,
      "32599": 1,
      "32600": 2,
      "32603": 3,
      "32604": 2,
      "32605": 2,
      "32606": 2,
      "32607": 1,
      "32608": 2,
      "32609": 1,
      "32610": 2,
      "32612": 1,
      "32613": 2,
      "32616": 1,
      "32620": 1,
      "32625": 1,
      "32626": 1,
      "32628": 1,
      "32631": 1,
      "32632": 1,
      "32634": 1,
      "32636": 1,
      "32641": 1,
      "32645": 1,
      "32649": 1,
      "32655": 2,
      "32658": 1,
      "32659": 1,
      "32662": 1,
      "32664": 1,
      "32667": 1,
      "32668": 1,
      "32671": 2,
      "32672": 3,
      "32674": 1,
      "32675": 1
   },
   "started": "2020-08-19T07:38:59.074Z",
   "trafficStats": {
      "incomingCompressionRatio": 0.8553811645507813,
      "incomingOctetsAppLevel": 32768000,
      "incomingOctetsWebSocketLevel": 28029130,
      "incomingOctetsWireLevel": 28033130,
      "incomingWebSocketFrames": 1000,
      "incomingWebSocketMessages": 1000,
      "incomingWebSocketOverhead": 0.00014270867486789637,
      "outgoingCompressionRatio": 0.8557799987792969,
      "outgoingOctetsAppLevel": 32768000,
      "outgoingOctetsWebSocketLevel": 28042199,
      "outgoingOctetsWireLevel": 28921625,
      "outgoingWebSocketFrames": 110063,
      "outgoingWebSocketMessages": 1000,
      "outgoingWebSocketOverhead": 0.031360807331835855,
      "preopenIncomingOctetsWireLevel": 278,
      "preopenOutgoingOctetsWireLevel": 338
   },
   "txFrameStats": {
      "0": 109063,
      "2": 1000,
      "8": 1
   },
   "txOctetStats": {
      "6": 8,
      "7": 2,
      "8": 5,
      "9": 6,
      "10": 10,
      "11": 5,
      "12": 8,
      "13": 6,
      "14": 7,
      "15": 6,
      "16": 4,
      "17": 7,
      "18": 2,
      "19": 2,
      "20": 5,
      "21": 2,
      "22": 5,
      "23": 3,
      "24": 7,
      "25": 3,
      "26": 6,
      "27": 5,
      "28": 5,
      "29": 7,
      "30": 6,
      "31": 7,
      "32": 2,
      "33": 4,
      "35": 2,
      "36": 2,
      "37": 3,
      "38": 5,
      "39": 5,
      "40": 4,
      "41": 6,
      "42": 3,
      "43": 8,
      "44": 4,
      "45": 3,
      "46": 4,
      "47": 2,
      "48": 5,
      "49": 1,
      "50": 2,
      "51": 2,
      "52": 6,
      "53": 4,
      "54": 2,
      "55": 2,
      "56": 8,
      "57": 4,
      "58": 4,
      "59": 4,
      "60": 7,
      "61": 6,
      "62": 5,
      "63": 6,
      "64": 4,
      "66": 3,
      "67": 2,
      "68": 5,
      "69": 3,
      "70": 6,
      "71": 3,
      "72": 4,
      "73": 6,
      "74": 3,
      "75": 3,
      "76": 1,
      "77": 3,
      "78": 5,
      "79": 3,
      "80": 6,
      "81": 2,
      "82": 1,
      "83": 4,
      "84": 3,
      "85": 4,
      "86": 2,
      "87": 3,
      "88": 4,
      "89": 7,
      "90": 4,
      "91": 7,
      "92": 3,
      "93": 8,
      "94": 3,
      "95": 7,
      "96": 5,
      "97": 6,
      "98": 8,
      "99": 2,
      "100": 5,
      "102": 4,
      "103": 4,
      "104": 1,
      "105": 4,
      "106": 7,
      "107": 8,
      "108": 1,
      "109": 2,
      "110": 5,
      "111": 8,
      "112": 4,
      "113": 3,
      "114": 2,
      "115": 6,
      "116": 6,
      "117": 2,
      "118": 6,
      "119": 6,
      "120": 5,
      "121": 5,
      "122": 3,
      "123": 2,
      "124": 3,
      "125": 4,
      "126": 3,
      "127": 4,
      "128": 3,
      "129": 8,
      "130": 9,
      "134": 1,
      "135": 2,
      "136": 2,
      "137": 3,
      "138": 1,
      "139": 1,
      "140": 4,
      "141": 3,
      "142": 5,
      "143": 7,
      "144": 5,
      "145": 3,
      "146": 1,
      "147": 2,
      "148": 4,
      "149": 3,
      "150": 1,
      "151": 4,
      "152": 3,
      "153": 2,
      "154": 2,
      "155": 4,
      "156": 3,
      "157": 2,
      "158": 4,
      "159": 5,
      "160": 5,
      "161": 5,
      "162": 5,
      "163": 4,
      "164": 5,
      "165": 4,
      "166": 3,
      "167": 3,
      "168": 1,
      "169": 1,
      "171": 6,
      "172": 3,
      "173": 6,
      "174": 3,
      "175": 6,
      "176": 4,
      "177": 3,
      "178": 5,
      "179": 2,
      "180": 1,
      "181": 5,
      "184": 3,
      "185": 3,
      "186": 1,
      "187": 3,
      "188": 1,
      "189": 1,
      "190": 2,
      "191": 5,
      "192": 3,
      "194": 6,
      "195": 7,
      "196": 3,
      "197": 4,
      "198": 5,
      "199": 2,
      "200": 5,
      "201": 3,
      "202": 7,
      "203": 7,
      "204": 1,
      "205": 1,
      "206": 5,
      "207": 5,
      "208": 6,
      "209": 7,
      "210": 3,
      "211": 5,
      "213": 8,
      "214": 5,
      "215": 3,
      "216": 1,
      "217": 5,
      "218": 8,
      "219": 2,
      "220": 2,
      "221": 6,
      "222": 8,
      "223": 6,
      "224": 3,
      "225": 7,
      "226": 3,
      "227": 4,
      "228": 3,
      "229": 5,
      "230": 4,
      "231": 8,
      "232": 3,
      "233": 4,
      "234": 6,
      "235": 5,
      "236": 4,
      "237": 2,
      "238": 5,
      "239": 3,
      "240": 2,
      "242": 3,
      "243": 3,
      "244": 3,
      "245": 3,
      "246": 3,
      "247": 4,
      "250": 3,
      "251": 2,
      "252": 3,
      "253": 4,
      "254": 3,
      "255": 6,
      "256": 1,
      "257": 7,
      "258": 8,
      "259": 1,
      "260": 4,
      "261": 4,
      "262": 4,
      "263": 6,
      "264": 109063,
      "338": 1
   },
   "wasClean": true,
   "wasCloseHandshakeTimeout": false,
   "wasNotCleanReason": null,
   "wasOpenHandshakeTimeout": false,
   "wasServerConnectionDropTimeout": false,
   "wirelog": [
      [
         "TO",
         [
            338,
            "474554202f20485454502f312e310d0a557365722d4167656e743a204175746f6261686e5465737453756974652f302e382e312d302e31302e390d0a486f7374 ..."
         ],
         false
      ],
      [
         "RO",
         [
            278,
            "485454502f312e312031303120537769746368696e672050726f746f636f6c730d0a5365632d576562736f636b65742d457874656e73696f6e733a207065726d ..."
         ]
      ],
      [
         "WLM",
         false
      ],
      [
         "TI",
         480
      ],
      [
         "WLM",
         true
      ],
      [
         "TF",
         [
            2,
            "0x03e8"
         ],
         8,
         true,
         0,
         "f5c8c378",
         null,
         null,
         false
      ],
      [
         "TO",
         [
            8,
            "8882f5c8c378f620"
         ],
         false
      ],
      [
         "RO",
         [
            4,
            "880203e8"
         ]
      ],
      [
         "RF",
         [
            2,
            "0x03e8"
         ],
         8,
         true,
         0,
         false,
         null
      ]
   ]
}