{
   "agent": "WSServer (HTTP)",
   "behavior": "OK",
   "behaviorClose": "OK",
   "case": 514,
   "closedByMe": true,
   "createStats": true,
   "createWirelog": true,
   "description": "Send 1000 compressed messages each of payload size 131072, auto-fragment to 256 octets. Use permessage-deflate client offers (requestNoContextTakeover, requestMaxWindowBits): [(True, 8), (True, 0), (False, 0)]",
   "droppedByMe": false,
   "duration": 14172,
   "expectation": "Receive echo'ed messages (with payload as sent). Timeout case after 480 secs.",
   "expected": {},
   "expectedClose": {
      "closeCode": [
         1000
      ],
      "closedByMe": true,
      "requireClean": true
   },
   "failedByMe": false,
   "httpRequest": "GET / HTTP/1.1\r\nUser-Agent: AutobahnTestSuite/0.8.1-0.10.9\r\nHost: 127.0.0.1:9010\r\nUpgrade: WebSocket\r\nConnection: Upgrade\r\nPragma: no-cache\r\nCache-Control: no-cache\r\nSec-WebSocket-Key: 2YdqW2i4MAyXl6lEnFZRKw==\r\nSec-WebSocket-Extensions: permessage-deflate; client_no_context_takeover; client_max_window_bits; server_no_context_takeover; server_max_window_bits=8, permessage-deflate; client_no_context_takeover; client_max_window_bits; server_no_context_takeover, permessage-deflate; client_no_context_takeover; client_max_window_bits\r\nSec-WebSocket-Version: 13\r\n\r\n",
   "httpResponse": "HTTP/1.1 101 Switching Protocols\r\nSec-Websocket-Extensions: permessage-deflate;server_no_context_takeover;client_no_context_takeover;client_max_window_bits=10;server_max_window_bits=9\r\nSec-Websocket-Accept: 4pdnsSqpzC61rohqfILEMAGzLYg=\r\nUpgrade: websocket\r\nConnection: Upgrade\r\nServer: WSServer/2.0.0\r\n\r\n",
   "id": "13.7.15",
   "isServer": false,
   "localCloseCode": 1000,
   "localCloseReason": null,
   "received": [],
   "remoteCloseCode": 1000,
   "remoteCloseReason": null,
   "reportCompressionRatio": true,
   "reportTime": true,
   "result": "Ok, received all echo'ed messages in time.",
   "resultClose": "Connection was properly closed",
   "rxFrameStats": {
      "0": 18001,
      "1": 1000,
      "8": 1
   },
   "rxOctetStats": {
      "4": 1,
      "304": 1,
      "4823": 2,
      "4825": 2,
      "4828": 2,
      "4829": 2,
      "4830": 5,
      "4833": 1,
      "4834": 3,
      "4835": 4,
      "4836": 5,
      "4837": 6,
      "4838": 2,
      "4839": 4,
      "4840": 2,
      "4841": 4,
      "4842": 7,
      "4843": 3,
      "4844": 1,
      "4846": 3,
      "4847": 2,
      "4848": 3,
      "4849": 3,
      "4853": 2,
      "4854": 1,
      "4855": 3,
      "4856": 1,
      "4857": 4,
      "4862": 2,
      "4865": 2,
      "4866": 1,
      "4867": 1,
      "4868": 2,
      "4869": 2,
      "4871": 6,
      "4873": 2,
      "4874": 1,
      "4876": 1,
      "4878": 1,
      "4879": 3,
      "4882": 1,
      "4884": 1,
      "4885": 1,
      "4886": 1,
      "4888": 3,
      "4889": 2,
      "4890": 4,
      "4891": 1,
      "4892": 2,
      "4894": 2,
      "4895": 2,
      "4896": 1,
      "4897": 1,
      "4899": 1,
      "4900": 1,
      "4902": 2,
      "4903": 1,
      "4905": 1,
      "4906": 1,
      "4907": 1,
      "4909": 1,
      "4918": 1,
      "4919": 2,
      "4921": 2,
      "4922": 1,
      "4925": 3,
      "4926": 2,
      "4927": 4,
      "4928": 3,
      "4931": 3,
      "4932": 4,
      "4933": 2,
      "4934": 6,
      "4935": 3,
      "4936": 3,
      "4937": 4,
      "4938": 3,
      "4939": 1,
      "4940": 2,
      "4941": 2,
      "4942": 4,
      "4943": 1,
      "4944": 2,
      "4945": 2,
      "4947": 2,
      "4948": 3,
      "4949": 6,
      "4950": 7,
      "4951": 1,
      "4952": 3,
      "4953": 2,
      "4955": 3,
      "4956": 4,
      "4957": 5,
      "4958": 5,
      "4959": 10,
      "4960": 9,
      "4961": 4,
      "4962": 4,
      "4963": 5,
      "4964": 5,
      "4966": 3,
      "4967": 3,
      "4968": 3,
      "4969": 1,
      "4970": 1,
      "4982": 1,
      "4985": 1,
      "4986": 2,
      "4988": 2,
      "4989": 1,
      "4990": 1,
      "4991": 1,
      "4995": 1,
      "4996": 1,
      "4998": 1,
      "4999": 1,
      "5000": 1,
      "5002": 1,
      "5004": 2,
      "5005": 1,
      "5006": 1,
      "5007": 1,
      "5010": 3,
      "5011": 1,
      "5013": 1,
      "5014": 4,
      "5015": 1,
      "5016": 1,
      "5017": 3,
      "5018": 4,
      "5019": 2,
      "5020": 2,
      "5021": 2,
      "5022": 1,
      "5024": 2,
      "5025": 1,
      "5026": 1,
      "5027": 1,
      "5028": 2,
      "5029": 1,
      "5030": 2,
      "5031": 3,
      "5032": 1,
      "5034": 1,
      "5035": 1,
      "5036": 2,
      "5037": 2,
      "5038": 3,
      "5039": 1,
      "5041": 2,
      "5043": 1,
      "5044": 1,
      "5046": 2,
      "5048": 1,
      "5049": 3,
      "5050": 1,
      "5051": 1,
      "5052": 2,
      "5053": 4,
      "5054": 4,
      "5055": 1,
      "5056": 2,
      "5058": 3,
      "5059": 1,
      "5060": 3,
      "5066": 3,
      "5067": 2,
      "5068": 5,
      "5069": 2,
      "5070": 9,
      "5071": 3,
      "5072": 11,
      "5073": 7,
      "5074": 8,
      "5075": 10,
      "5076": 6,
      "5077": 6,
      "5078": 3,
      "5079": 3,
      "5080": 7,
      "5081": 6,
      "5082": 3,
      "5084": 3,
      "5085": 4,
      "5086": 6,
      "5087": 4,
      "5088": 4,
      "5089": 1,
      "5091": 2,
      "5092": 3,
      "5094": 4,
      "5095": 1,
      "5098": 1,
      "5100": 1,
      "5101": 1,
      "5103": 1,
      "5105": 1,
      "5106": 1,
      "5107": 2,
      "5108": 1,
      "5109": 3,
      "5110": 3,
      "5112": 1,
      "5113": 1,
      "5114": 1,
      "5115": 1,
      "5117": 1,
      "5119": 2,
      "5120": 3,
      "5121": 3,
      "5122": 1,
      "5123": 3,
      "5124": 5,
      "5125": 5,
      "5126": 6,
      "5127": 11,
      "5128": 7,
      "5129": 9,
      "5130": 11,
      "5131": 3,
      "5132": 3,
      "5133": 5,
      "5134": 12,
      "5135": 9,
      "5136": 6,
      "5137": 6,
      "5138": 5,
      "5139": 5,
      "5140": 6,
      "5141": 4,
      "5142": 4,
      "5143": 3,
      "5144": 2,
      "5145": 5,
      "5146": 4,
      "5147": 4,
      "5148": 4,
      "5149": 7,
      "5150": 5,
      "5151": 13,
      "5152": 8,
      "5153": 12,
      "5154": 4,
      "5155": 8,
      "5156": 11,
      "5157": 6,
      "5158": 7,
      "5159": 6,
      "5160": 8,
      "5161": 7,
      "5162": 3,
      "5163": 6,
      "5164": 1,
      "5165": 1,
      "5166": 5,
      "5167": 3,
      "5168": 6,
      "5169": 4,
      "5170": 4,
      "5171": 3,
      "5172": 7,
      "5173": 7,
      "5174": 7,
      "5175": 15,
      "5176": 11,
      "5177": 19,
      "5178": 12,
      "5179": 11,
      "5180": 14,
      "5181": 11,
      "5182": 12,
      "5183": 9,
      "5184": 4,
      "5185": 2,
      "5186": 5,
      "5187": 5,
      "5188": 3,
      "5189": 1,
      "5190": 1,
      "5191": 1,
      "5194": 1,
      "5197": 1,
      "5198": 2,
      "5200": 1,
      "5201": 1,
      "5204": 1,
      "5205": 1,
      "5206": 1,
      "5210": 1,
      "5212": 2,
      "5219": 1,
      "5220": 2,
      "5221": 2,
      "5222": 1,
      "5223": 1,
      "5224": 1,
      "5227": 1
   },
   "started": "2020-02-21T20:25:37.943Z",
   "trafficStats": {
      "incomingCompressionRatio": 0.03805109405517578,
      "incomingOctetsAppLevel": 131072000,
      "incomingOctetsWebSocketLevel": 4987433,
      "incomingOctetsWireLevel": 5063437,
      "incomingWebSocketFrames": 19001,
      "incomingWebSocketMessages": 1000,
      "incomingWebSocketOverhead": 0.015239101958863407,
      "outgoingCompressionRatio": 0.0363199462890625,
      "outgoingOctetsAppLevel": 131072000,
      "outgoingOctetsWebSocketLevel": 4760528,
      "outgoingOctetsWireLevel": 4911886,
      "outgoingWebSocketFrames": 19001,
      "outgoingWebSocketMessages": 1000,
      "outgoingWebSocketOverhead": 0.03179437238894509,
      "preopenIncomingOctetsWireLevel": 304,
      "preopenOutgoingOctetsWireLevel": 564
   },
   "txFrameStats": {
      "0": 18001,
      "1": 1000,
      "8": 1
   },
   "txOctetStats": {
      "6": 12,
      "7": 8,
      "8": 6,
      "9": 3,
      "10": 7,
      "11": 5,
      "12": 8,
      "13": 3,
      "14": 4,
      "15": 1,
      "16": 1,
      "17": 1,
      "18": 2,
      "20": 3,
      "21": 1,
      "22": 3,
      "23": 1,
      "25": 3,
      "26": 2,
      "27": 3,
      "28": 2,
      "29": 1,
      "30": 1,
      "31": 2,
      "33": 2,
      "35": 1,
      "36": 1,
      "37": 4,
      "38": 1,
      "39": 4,
      "40": 3,
      "41": 2,
      "43": 5,
      "44": 5,
      "46": 3,
      "47": 2,
      "49": 2,
      "51": 1,
      "53": 3,
      "54": 2,
      "55": 1,
      "56": 5,
      "57": 2,
      "58": 3,
      "59": 5,
      "60": 2,
      "61": 4,
      "62": 1,
      "63": 3,
      "64": 9,
      "65": 5,
      "66": 3,
      "67": 8,
      "68": 5,
      "69": 2,
      "70": 3,
      "71": 4,
      "72": 1,
      "73": 8,
      "75": 4,
      "76": 3,
      "77": 6,
      "78": 3,
      "79": 4,
      "80": 12,
      "81": 4,
      "82": 6,
      "83": 5,
      "84": 5,
      "85": 5,
      "86": 4,
      "87": 2,
      "88": 4,
      "91": 1,
      "92": 1,
      "93": 1,
      "94": 2,
      "95": 3,
      "96": 1,
      "97": 1,
      "99": 1,
      "101": 1,
      "104": 2,
      "108": 1,
      "110": 2,
      "111": 2,
      "112": 3,
      "113": 2,
      "114": 1,
      "115": 1,
      "117": 4,
      "118": 4,
      "119": 3,
      "120": 2,
      "121": 4,
      "122": 1,
      "123": 3,
      "124": 2,
      "125": 2,
      "127": 4,
      "128": 2,
      "129": 2,
      "130": 1,
      "131": 1,
      "134": 1,
      "135": 3,
      "136": 1,
      "137": 3,
      "139": 1,
      "142": 1,
      "143": 1,
      "147": 1,
      "148": 1,
      "150": 1,
      "152": 2,
      "154": 3,
      "155": 2,
      "156": 6,
      "157": 3,
      "159": 5,
      "160": 5,
      "161": 2,
      "162": 6,
      "163": 9,
      "164": 6,
      "165": 9,
      "166": 4,
      "167": 6,
      "168": 7,
      "169": 3,
      "170": 3,
      "171": 3,
      "172": 9,
      "173": 9,
      "174": 12,
      "175": 9,
      "176": 7,
      "177": 8,
      "178": 4,
      "179": 2,
      "180": 2,
      "181": 2,
      "182": 7,
      "183": 7,
      "184": 6,
      "185": 7,
      "186": 3,
      "187": 9,
      "188": 8,
      "189": 11,
      "190": 9,
      "191": 7,
      "192": 8,
      "193": 9,
      "194": 9,
      "195": 6,
      "196": 8,
      "197": 6,
      "198": 2,
      "199": 5,
      "200": 4,
      "201": 4,
      "202": 6,
      "203": 3,
      "204": 8,
      "205": 4,
      "206": 3,
      "207": 10,
      "208": 7,
      "209": 8,
      "210": 5,
      "211": 8,
      "212": 6,
      "213": 3,
      "214": 4,
      "215": 5,
      "216": 8,
      "217": 6,
      "218": 9,
      "219": 8,
      "220": 17,
      "221": 8,
      "222": 10,
      "223": 8,
      "224": 10,
      "225": 5,
      "226": 16,
      "227": 17,
      "228": 14,
      "229": 5,
      "230": 14,
      "231": 10,
      "232": 7,
      "233": 7,
      "234": 3,
      "235": 3,
      "236": 5,
      "237": 5,
      "238": 2,
      "239": 3,
      "240": 8,
      "241": 3,
      "242": 2,
      "244": 1,
      "247": 1,
      "249": 4,
      "251": 4,
      "252": 1,
      "253": 3,
      "254": 1,
      "255": 7,
      "256": 7,
      "257": 6,
      "258": 10,
      "259": 5,
      "260": 8,
      "261": 10,
      "262": 10,
      "263": 7,
      "264": 18001,
      "564": 1
   },
   "wasClean": true,
   "wasCloseHandshakeTimeout": false,
   "wasNotCleanReason": null,
   "wasOpenHandshakeTimeout": false,
   "wasServerConnectionDropTimeout": false,
   "wirelog": [
      [
         "TO",
         [
            564,
            "474554202f20485454502f312e310d0a557365722d4167656e743a204175746f6261686e5465737453756974652f302e382e312d302e31302e390d0a486f7374 ..."
         ],
         false
      ],
      [
         "RO",
         [
            304,
            "485454502f312e312031303120537769746368696e672050726f746f636f6c730d0a5365632d576562736f636b65742d457874656e73696f6e733a207065726d ..."
         ]
      ],
      [
         "WLM",
         false
      ],
      [
         "TI",
         480
      ],
      [
         "WLM",
         true
      ],
      [
         "TF",
         [
            2,
            "0x03e8"
         ],
         8,
         true,
         0,
         "f2f8fc1d",
         null,
         null,
         false
      ],
      [
         "TO",
         [
            8,
            "8882f2f8fc1df110"
         ],
         false
      ],
      [
         "RO",
         [
            4,
            "880203e8"
         ]
      ],
      [
         "RF",
         [
            2,
            "0x03e8"
         ],
         8,
         true,
         0,
         false,
         null
      ]
   ]
}